[{"date":"2025-12-22","close":389.86},{"date":"2025-12-23","close":393.74},{"date":"2025-12-24","close":393.18},{"date":"2025-12-26","close":392.59},{"date":"2025-12-29","close":394.19},{"date":"2025-12-30","close":391.71},{"date":"2025-12-31","close":389.2},{"date":"2026-01-02","close":398.0},{"date":"2026-01-05","close":390.97},{"date":"2026-01-06","close":381.1},{"date":"2026-01-07","close":376.43},{"date":"2026-01-08","close":378.36},{"date":"2026-01-09","close":381.7},{"date":"2026-01-12","close":385.47},{"date":"2026-01-13","close":391.08},{"date":"2026-01-14","close":385.84},{"date":"2026-01-15","close":387.27},{"date":"2026-01-16","close":389.53},{"date":"2026-01-20","close":387.33},{"date":"2026-01-21","close":395.33},{"date":"2026-01-22","close":390.13},{"date":"2026-01-23","close":386.22},{"date":"2026-01-26","close":394.16},{"date":"2026-01-27","close":392.3},{"date":"2026-01-28","close":394.2},{"date":"2026-01-29","close":426.07},{"date":"2026-01-30","close":420.58},{"date":"2026-02-02","close":425.09},{"date":"2026-02-03","close":435.36},{"date":"2026-02-04","close":441.2},{"date":"2026-02-05","close":436.15},{"date":"2026-02-06","close":454.76},{"date":"2026-02-09","close":459.79},{"date":"2026-02-10","close":461.38},{"date":"2026-02-11","close":472.54},{"date":"2026-02-12","close":460.45},{"date":"2026-02-13","close":465.27},{"date":"2026-02-17","close":470.42},{"date":"2026-02-18","close":459.44},{"date":"2026-02-19","close":463.69},{"date":"2026-02-20","close":467.12},{"date":"2026-02-23","close":459.94},{"date":"2026-02-24","close":463.73},{"date":"2026-02-25","close":460.02},{"date":"2026-02-26","close":457.14},{"date":"2026-02-27","close":462.32},{"date":"2026-03-02","close":466.17},{"date":"2026-03-03","close":445.83},{"date":"2026-03-04","close":445.05},{"date":"2026-03-05","close":436.36},{"date":"2026-03-06","close":423.13},{"date":"2026-03-09","close":427.52},{"date":"2026-03-10","close":433.67},{"date":"2026-03-11","close":432.42},{"date":"2026-03-12","close":421.82},{"date":"2026-03-13","close":422.4},{"date":"2026-03-16","close":421.5},{"date":"2026-03-17","close":425.36},{"date":"2026-03-18","close":426.7},{"date":"2026-03-19","close":423.03},{"date":"2026-03-20","close":410.36},{"date":"2026-03-23","close":424.94},{"date":"2026-03-24","close":430.08},{"date":"2026-03-25","close":434.0},{"date":"2026-03-26","close":407.13},{"date":"2026-03-27","close":410.23},{"date":"2026-03-30","close":403.93},{"date":"2026-03-31","close":416.74},{"date":"2026-04-01","close":428.14},{"date":"2026-04-02","close":427.07},{"date":"2026-04-06","close":430.89},{"date":"2026-04-07","close":431.85},{"date":"2026-04-08","close":449.47},{"date":"2026-04-09","close":460.11},{"date":"2026-04-10","close":465.71},{"date":"2026-04-13","close":472.94},{"date":"2026-04-14","close":470.57},{"date":"2026-04-15","close":462.56},{"date":"2026-04-16","close":460.27},{"date":"2026-04-17","close":476.11},{"date":"2026-04-20","close":477.24},{"date":"2026-04-21","close":479.12},{"date":"2026-04-22","close":477.19},{"date":"2026-04-23","close":485.53},{"date":"2026-04-24","close":486.42},{"date":"2026-04-27","close":485.9},{"date":"2026-04-28","close":480.75},{"date":"2026-04-29","close":479.37},{"date":"2026-04-30","close":492.54},{"date":"2026-05-01","close":486.48},{"date":"2026-05-04","close":486.5},{"date":"2026-05-05","close":477.45},{"date":"2026-05-06","close":488.18},{"date":"2026-05-07","close":469.81},{"date":"2026-05-08","close":466.17},{"date":"2026-05-11","close":476.5},{"date":"2026-05-12","close":467.66},{"date":"2026-05-13","close":471.02},{"date":"2026-05-14","close":481.67},{"date":"2026-05-15","close":466.6},{"date":"2026-05-18","close":460.42},{"date":"2026-05-19","close":448.01},{"date":"2026-05-20","close":451.69},{"date":"2026-05-21","close":447.64},{"date":"2026-05-22","close":451.02},{"date":"2026-05-26","close":461.43},{"date":"2026-05-27","close":457.68},{"date":"2026-05-28","close":452.26},{"date":"2026-05-29","close":451.3},{"date":"2026-06-01","close":448.47},{"date":"2026-06-02","close":458.92},{"date":"2026-06-03","close":465.84},{"date":"2026-06-04","close":463.76},{"date":"2026-06-05","close":456.84},{"date":"2026-06-08","close":458.92},{"date":"2026-06-09","close":470.76},{"date":"2026-06-10","close":449.12},{"date":"2026-06-11","close":460.14},{"date":"2026-06-12","close":458.25},{"date":"2026-06-15","close":472.54},{"date":"2026-06-16","close":475.34},{"date":"2026-06-17","close":472.51},{"date":"2026-06-18","close":483.4},{"date":"2026-06-22","close":491.59},{"date":"2026-06-23","close":474.34},{"date":"2026-06-24","close":483.15},{"date":"2026-06-25","close":503.46},{"date":"2026-06-26","close":477.89},{"date":"2026-06-29","close":480.35},{"date":"2026-06-30","close":491.16},{"date":"2026-07-01","close":484.58}]