[{"date":"2025-12-29","close":90.53},{"date":"2025-12-30","close":90.79},{"date":"2025-12-31","close":89.92},{"date":"2026-01-02","close":90.02},{"date":"2026-01-05","close":92.65},{"date":"2026-01-06","close":94.75},{"date":"2026-01-07","close":92.67},{"date":"2026-01-08","close":94.08},{"date":"2026-01-09","close":92.85},{"date":"2026-01-12","close":91.45},{"date":"2026-01-13","close":88.34},{"date":"2026-01-14","close":89.24},{"date":"2026-01-15","close":88.75},{"date":"2026-01-16","close":87.31},{"date":"2026-01-20","close":86.8},{"date":"2026-01-21","close":86.55},{"date":"2026-01-22","close":87.54},{"date":"2026-01-23","close":86.6},{"date":"2026-01-26","close":87.32},{"date":"2026-01-27","close":85.99},{"date":"2026-01-28","close":85.71},{"date":"2026-01-29","close":86.02},{"date":"2026-01-30","close":87.07},{"date":"2026-02-02","close":86.22},{"date":"2026-02-03","close":86.18},{"date":"2026-02-04","close":88.09},{"date":"2026-02-05","close":88.73},{"date":"2026-02-06","close":89.91},{"date":"2026-02-09","close":89.73},{"date":"2026-02-10","close":91.4},{"date":"2026-02-11","close":95.61},{"date":"2026-02-12","close":95.18},{"date":"2026-02-13","close":96.45},{"date":"2026-02-17","close":97.15},{"date":"2026-02-18","close":98.25},{"date":"2026-02-19","close":99.25},{"date":"2026-02-20","close":98.75},{"date":"2026-02-23","close":99.46},{"date":"2026-02-24","close":99.87},{"date":"2026-02-25","close":99.85},{"date":"2026-02-26","close":100.99},{"date":"2026-02-27","close":98.44},{"date":"2026-03-02","close":99.49},{"date":"2026-03-03","close":97.97},{"date":"2026-03-04","close":95.75},{"date":"2026-03-05","close":93.45},{"date":"2026-03-06","close":94.11},{"date":"2026-03-09","close":93.28},{"date":"2026-03-10","close":91.7},{"date":"2026-03-11","close":93.73},{"date":"2026-03-12","close":92.59},{"date":"2026-03-13","close":93.2},{"date":"2026-03-16","close":93.3},{"date":"2026-03-17","close":92.52},{"date":"2026-03-18","close":89.08},{"date":"2026-03-19","close":89.84},{"date":"2026-03-20","close":87.87},{"date":"2026-03-23","close":87.8},{"date":"2026-03-24","close":86.32},{"date":"2026-03-25","close":87.64},{"date":"2026-03-26","close":89.15},{"date":"2026-03-27","close":88.57},{"date":"2026-03-30","close":88.62},{"date":"2026-03-31","close":90.42},{"date":"2026-04-01","close":91.03},{"date":"2026-04-02","close":90.89},{"date":"2026-04-06","close":91.0},{"date":"2026-04-07","close":91.4},{"date":"2026-04-08","close":93.01},{"date":"2026-04-09","close":93.03},{"date":"2026-04-10","close":93.12},{"date":"2026-04-13","close":95.34},{"date":"2026-04-14","close":96.52},{"date":"2026-04-15","close":94.2},{"date":"2026-04-16","close":94.78},{"date":"2026-04-17","close":94.78},{"date":"2026-04-20","close":95.48},{"date":"2026-04-21","close":92.69},{"date":"2026-04-22","close":93.04},{"date":"2026-04-23","close":92.44},{"date":"2026-04-24","close":91.26},{"date":"2026-04-27","close":92.59},{"date":"2026-04-28","close":82.8},{"date":"2026-04-29","close":80.07},{"date":"2026-04-30","close":82.43},{"date":"2026-05-01","close":82.9},{"date":"2026-05-04","close":82.67},{"date":"2026-05-05","close":83.01},{"date":"2026-05-06","close":82.83},{"date":"2026-05-07","close":83.37},{"date":"2026-05-08","close":82.33},{"date":"2026-05-11","close":79.58},{"date":"2026-05-12","close":83.37},{"date":"2026-05-13","close":82.72},{"date":"2026-05-14","close":82.65},{"date":"2026-05-15","close":83.7},{"date":"2026-05-18","close":85.14},{"date":"2026-05-19","close":86.08},{"date":"2026-05-20","close":85.38},{"date":"2026-05-21","close":85.31},{"date":"2026-05-22","close":85.5},{"date":"2026-05-26","close":84.41},{"date":"2026-05-27","close":82.56},{"date":"2026-05-28","close":82.82},{"date":"2026-05-29","close":82.33},{"date":"2026-06-01","close":82.94},{"date":"2026-06-02","close":83.75},{"date":"2026-06-03","close":84.98},{"date":"2026-06-04","close":86.69},{"date":"2026-06-05","close":87.33},{"date":"2026-06-08","close":87.27},{"date":"2026-06-09","close":89.63},{"date":"2026-06-10","close":88.17},{"date":"2026-06-11","close":87.14},{"date":"2026-06-12","close":88.57},{"date":"2026-06-15","close":88.26},{"date":"2026-06-16","close":89.33},{"date":"2026-06-17","close":87.16},{"date":"2026-06-18","close":87.97},{"date":"2026-06-22","close":87.09},{"date":"2026-06-23","close":87.57},{"date":"2026-06-24","close":90.56},{"date":"2026-06-25","close":90.96},{"date":"2026-06-26","close":93.1},{"date":"2026-06-29","close":91.24},{"date":"2026-06-30","close":86.09},{"date":"2026-07-01","close":84.17},{"date":"2026-07-02","close":87.47},{"date":"2026-07-06","close":89.76},{"date":"2026-07-07","close":89.41},{"date":"2026-07-08","close":87.56},{"date":"2026-07-09","close":89.23},{"date":"2026-07-10","close":91.34},{"date":"2026-07-13","close":94.08},{"date":"2026-07-14","close":91.03}]