{"company": "AbbVie", "mentions": [{"date": "2026-05-29", "sentiment": "wait_hold_neutral", "segment": "closing_commentary", "note": "Acquired Exact Sciences; Cramer uncertain on integration outcome pending clarity on deal structure.", "closing_price": 217.72}, {"date": "2026-04-07", "sentiment": "caution_concern", "segment": "opening_commentary", "note": "Down; pharma sector weakness across the board signaling inflationary concerns.", "closing_price": 206.37}, {"date": "2026-01-30", "sentiment": "buy", "segment": "caller_qa", "note": "Reports this week with very good quarter expected; like the dividend but Astroenica has better portfolio at this moment.", "closing_price": 223.01}], "sector": "Healthcare", "style": "growth", "industry": "Drug Manufacturers - General", "pe_ratio": 105.6, "market_cap": 382492999680, "market_cap_category": "mega"}