{"company": "Amprius Technologies", "mentions": [{"date": "2026-01-09", "sentiment": "buy", "segment": "lightning_round", "note": "Interesting spec; makes batteries for drones and satellites; nice pullback; good one to own after Ford exited battery business.", "closing_price": 9.48}, {"date": "2026-05-01", "sentiment": "buy", "segment": "lightning_round", "note": "Energy-storage battery SPAC. Makes sense fundamentally. Cramer holds one SPAC in model portfolio of five per his book guidance.", "closing_price": 20.87}], "sector": "Industrials", "style": "", "industry": "Electrical Equipment & Parts", "pe_ratio": null, "market_cap": 1828406656, "market_cap_category": "small", "price_latest": 12.22, "price_latest_date": "2026-06-25", "pct_right_daily": 72.8, "n_right_days": 114}