{"company": "Amphenol", "mentions": [{"date": "2026-05-08", "sentiment": "buy", "segment": "lightning_round", "note": "Come down a little from highs; good opportunity; connectivity play benefiting from data center buildout.", "closing_price": 128.03}], "sector": "Technology", "style": "growth", "industry": "Electronic Components", "pe_ratio": 46.91, "market_cap": 201414000640, "market_cap_category": "mega", "price_latest": 166.43, "price_latest_date": "2026-06-25", "pct_right_daily": 75.0, "n_right_days": 32}