{"company": "Ashland Global Holdings", "mentions": [{"date": "2026-06-16", "sentiment": "buy", "segment": "lightning_round", "note": "Anor partnership positioned to unlock significant value. Stock well below intrinsic; urge holders to stick with position. Should go higher.", "closing_price": 64.56}], "sector": "Basic Materials", "industry": "Specialty Chemicals", "style": "", "pe_ratio": null, "market_cap": 2927670272, "market_cap_category": "mid", "price_latest": 64.46, "price_latest_date": "2026-06-25", "pct_right_daily": 33.3, "n_right_days": 6, "days_right": {"buy": {"pct": 33.3, "n": 6, "small_sample": true}, "combined": {"pct": 33.3, "n": 6, "small_sample": true}}}