{"window_days":60,"min_calls":3,"tickers":{"GS":{"n":12,"median":9.89,"mean":4.3,"win_rate":66.7,"spy_median":4.04,"qqq_median":9.29,"excess_spy_median":3.23,"excess_qqq_median":-4.8,"beat_spy_pct":58.3,"beat_qqq_pct":25.0,"best":19.6,"worst":-18.6},"C":{"n":6,"median":-7.34,"mean":-4.29,"win_rate":33.3,"spy_median":-2.08,"qqq_median":-2.73,"excess_spy_median":-4.56,"excess_qqq_median":-8.51,"beat_spy_pct":0.0,"beat_qqq_pct":0.0,"best":8.3,"worst":-13.6},"COF":{"n":11,"median":-15.03,"mean":-11.66,"win_rate":9.1,"spy_median":-1.95,"qqq_median":-2.51,"excess_spy_median":-12.5,"excess_qqq_median":-17.87,"beat_spy_pct":0.0,"beat_qqq_pct":0.0,"best":5.9,"worst":-28.0},"JNJ":{"n":12,"median":1.52,"mean":3.67,"win_rate":66.7,"spy_median":3.84,"qqq_median":8.77,"excess_spy_median":0.86,"excess_qqq_median":-4.82,"beat_spy_pct":50.0,"beat_qqq_pct":50.0,"best":17.7,"worst":-8.5},"LLY":{"n":9,"median":-4.91,"mean":-1.2,"win_rate":33.3,"spy_median":3.09,"qqq_median":8.44,"excess_spy_median":-4.44,"excess_qqq_median":-9.26,"beat_spy_pct":11.1,"beat_qqq_pct":11.1,"best":31.6,"worst":-16.7},"HOOD":{"n":5,"median":-6.88,"mean":-12.88,"win_rate":20.0,"spy_median":3.03,"qqq_median":7.5,"excess_spy_median":-11.64,"excess_qqq_median":-17.06,"beat_spy_pct":20.0,"beat_qqq_pct":20.0,"best":21.9,"worst":-37.4},"AEM":{"n":9,"median":-10.22,"mean":-2.05,"win_rate":44.4,"spy_median":-3.02,"qqq_median":-2.95,"excess_spy_median":-1.72,"excess_qqq_median":-0.16,"beat_spy_pct":44.4,"beat_qqq_pct":44.4,"best":26.2,"worst":-15.3},"LRCX":{"n":22,"median":4.29,"mean":10.12,"win_rate":86.4,"spy_median":-2.62,"qqq_median":-2.89,"excess_spy_median":6.26,"excess_qqq_median":6.02,"beat_spy_pct":86.4,"beat_qqq_pct":77.3,"best":46.1,"worst":-16.5},"PLTR":{"n":9,"median":-3.31,"mean":-4.59,"win_rate":22.2,"spy_median":3.67,"qqq_median":9.23,"excess_spy_median":-6.11,"excess_qqq_median":-12.7,"beat_spy_pct":11.1,"beat_qqq_pct":33.3,"best":9.7,"worst":-19.0},"KLAC":{"n":15,"median":2.44,"mean":6.23,"win_rate":60.0,"spy_median":-3.0,"qqq_median":-2.95,"excess_spy_median":4.7,"excess_qqq_median":4.69,"beat_spy_pct":80.0,"beat_qqq_pct":80.0,"best":34.6,"worst":-14.5},"INTC":{"n":16,"median":39.59,"mean":49.69,"win_rate":68.8,"spy_median":2.49,"qqq_median":6.93,"excess_spy_median":35.71,"excess_qqq_median":30.25,"beat_spy_pct":87.5,"beat_qqq_pct":87.5,"best":186.4,"worst":-19.0},"CRM":{"n":10,"median":-7.62,"mean":-8.37,"win_rate":10.0,"spy_median":4.22,"qqq_median":9.11,"excess_spy_median":-10.37,"excess_qqq_median":-16.82,"beat_spy_pct":10.0,"beat_qqq_pct":0.0,"best":12.3,"worst":-21.1},"SNOW":{"n":3,"median":-14.75,"mean":10.4,"win_rate":33.3,"spy_median":3.13,"qqq_median":7.71,"excess_spy_median":-17.34,"excess_qqq_median":-16.61,"beat_spy_pct":33.3,"beat_qqq_pct":33.3,"best":65.5,"worst":-19.6},"COST":{"n":9,"median":1.94,"mean":3.11,"win_rate":55.6,"spy_median":8.5,"qqq_median":15.83,"excess_spy_median":-6.95,"excess_qqq_median":-12.78,"beat_spy_pct":22.2,"beat_qqq_pct":22.2,"best":14.0,"worst":-5.3},"AAPL":{"n":22,"median":-0.51,"mean":2.6,"win_rate":45.5,"spy_median":-2.33,"qqq_median":-2.89,"excess_spy_median":3.23,"excess_qqq_median":1.22,"beat_spy_pct":86.4,"beat_qqq_pct":54.5,"best":19.0,"worst":-8.9},"NVDA":{"n":50,"median":1.44,"mean":5.38,"win_rate":52.0,"spy_median":3.9,"qqq_median":7.99,"excess_spy_median":1.17,"excess_qqq_median":-0.11,"beat_spy_pct":62.0,"beat_qqq_pct":46.0,"best":28.6,"worst":-14.2},"MU":{"n":26,"median":29.26,"mean":51.68,"win_rate":80.8,"spy_median":-0.0,"qqq_median":0.69,"excess_spy_median":32.45,"excess_qqq_median":31.91,"beat_spy_pct":88.5,"beat_qqq_pct":88.5,"best":181.5,"worst":-26.1},"AMAT":{"n":13,"median":16.01,"mean":20.25,"win_rate":92.3,"spy_median":1.33,"qqq_median":-0.25,"excess_spy_median":16.45,"excess_qqq_median":15.83,"beat_spy_pct":92.3,"beat_qqq_pct":84.6,"best":54.8,"worst":-2.9},"SBUX":{"n":6,"median":0.52,"mean":-0.05,"win_rate":50.0,"spy_median":-2.66,"qqq_median":-2.98,"excess_spy_median":0.3,"excess_qqq_median":2.97,"beat_spy_pct":66.7,"beat_qqq_pct":66.7,"best":11.5,"worst":-8.9},"HON":{"n":6,"median":10.63,"mean":8.15,"win_rate":66.7,"spy_median":-3.02,"qqq_median":-2.89,"excess_spy_median":13.65,"excess_qqq_median":13.52,"beat_spy_pct":83.3,"beat_qqq_pct":83.3,"best":21.6,"worst":-6.8},"AMZN":{"n":22,"median":-9.28,"mean":-4.31,"win_rate":22.7,"spy_median":3.45,"qqq_median":7.42,"excess_spy_median":-8.14,"excess_qqq_median":-10.64,"beat_spy_pct":13.6,"beat_qqq_pct":4.5,"best":25.5,"worst":-16.4},"OKE":{"n":3,"median":21.24,"mean":12.91,"win_rate":66.7,"spy_median":-1.95,"qqq_median":-2.51,"excess_spy_median":23.24,"excess_qqq_median":23.8,"beat_spy_pct":66.7,"beat_qqq_pct":66.7,"best":21.3,"worst":-3.8},"EPD":{"n":4,"median":11.43,"mean":9.05,"win_rate":75.0,"spy_median":1.07,"qqq_median":3.47,"excess_spy_median":5.99,"excess_qqq_median":2.42,"beat_spy_pct":50.0,"beat_qqq_pct":50.0,"best":18.9,"worst":-5.5},"TXRH":{"n":4,"median":-8.07,"mean":-8.86,"win_rate":0.0,"spy_median":-2.66,"qqq_median":-3.02,"excess_spy_median":-5.57,"excess_qqq_median":-5.05,"beat_spy_pct":0.0,"beat_qqq_pct":0.0,"best":-3.1,"worst":-16.2},"GOOGL":{"n":21,"median":-5.39,"mean":-0.59,"win_rate":42.9,"spy_median":3.03,"qqq_median":6.05,"excess_spy_median":-3.03,"excess_qqq_median":-4.92,"beat_spy_pct":23.8,"beat_qqq_pct":0.0,"best":26.6,"worst":-17.7},"MSFT":{"n":10,"median":-12.03,"mean":-8.59,"win_rate":10.0,"spy_median":2.86,"qqq_median":5.75,"excess_spy_median":-11.63,"excess_qqq_median":-12.96,"beat_spy_pct":0.0,"beat_qqq_pct":0.0,"best":16.6,"worst":-17.2},"META":{"n":18,"median":-7.16,"mean":-5.58,"win_rate":27.8,"spy_median":4.49,"qqq_median":11.66,"excess_spy_median":-11.44,"excess_qqq_median":-16.37,"beat_spy_pct":5.6,"beat_qqq_pct":11.1,"best":17.9,"worst":-27.4},"ORCL":{"n":5,"median":-11.24,"mean":-7.61,"win_rate":20.0,"spy_median":3.81,"qqq_median":6.05,"excess_spy_median":-7.13,"excess_qqq_median":-15.51,"beat_spy_pct":20.0,"beat_qqq_pct":20.0,"best":18.8,"worst":-22.4},"TSM":{"n":10,"median":3.77,"mean":5.53,"win_rate":80.0,"spy_median":-2.73,"qqq_median":-2.89,"excess_spy_median":4.44,"excess_qqq_median":3.93,"beat_spy_pct":100.0,"beat_qqq_pct":100.0,"best":23.6,"worst":-6.5},"TER":{"n":5,"median":22.16,"mean":22.18,"win_rate":100.0,"spy_median":4.0,"qqq_median":9.27,"excess_spy_median":18.15,"excess_qqq_median":12.88,"beat_spy_pct":100.0,"beat_qqq_pct":60.0,"best":34.9,"worst":6.0},"HD":{"n":7,"median":-7.87,"mean":-7.11,"win_rate":14.3,"spy_median":-1.95,"qqq_median":-2.51,"excess_spy_median":-9.33,"excess_qqq_median":-9.38,"beat_spy_pct":14.3,"beat_qqq_pct":14.3,"best":1.2,"worst":-14.0},"JPM":{"n":5,"median":-7.96,"mean":-6.85,"win_rate":20.0,"spy_median":-2.44,"qqq_median":-3.01,"excess_spy_median":-4.38,"excess_qqq_median":-8.73,"beat_spy_pct":0.0,"beat_qqq_pct":0.0,"best":4.4,"worst":-12.3},"CRWD":{"n":13,"median":54.46,"mean":27.98,"win_rate":69.2,"spy_median":8.12,"qqq_median":16.84,"excess_spy_median":44.23,"excess_qqq_median":35.7,"beat_spy_pct":69.2,"beat_qqq_pct":69.2,"best":98.9,"worst":-77.3},"PG":{"n":8,"median":-0.09,"mean":-0.56,"win_rate":50.0,"spy_median":-2.33,"qqq_median":-2.75,"excess_spy_median":2.3,"excess_qqq_median":3.42,"beat_spy_pct":62.5,"beat_qqq_pct":62.5,"best":12.4,"worst":-10.8},"PANW":{"n":6,"median":77.28,"mean":53.46,"win_rate":83.3,"spy_median":11.95,"qqq_median":21.98,"excess_spy_median":63.36,"excess_qqq_median":52.74,"beat_spy_pct":83.3,"beat_qqq_pct":83.3,"best":87.4,"worst":-14.9},"YUM":{"n":4,"median":-0.48,"mean":-0.21,"win_rate":50.0,"spy_median":3.61,"qqq_median":8.58,"excess_spy_median":-7.16,"excess_qqq_median":-12.12,"beat_spy_pct":25.0,"beat_qqq_pct":25.0,"best":6.2,"worst":-6.1},"MCD":{"n":4,"median":-6.26,"mean":-3.57,"win_rate":25.0,"spy_median":1.02,"qqq_median":3.31,"excess_spy_median":-5.79,"excess_qqq_median":-9.15,"beat_spy_pct":25.0,"beat_qqq_pct":25.0,"best":8.8,"worst":-10.5},"WFC":{"n":6,"median":-7.8,"mean":-7.63,"win_rate":16.7,"spy_median":0.35,"qqq_median":2.35,"excess_spy_median":-8.56,"excess_qqq_median":-14.02,"beat_spy_pct":0.0,"beat_qqq_pct":0.0,"best":3.5,"worst":-18.4},"BAC":{"n":5,"median":2.85,"mean":-1.94,"win_rate":60.0,"spy_median":7.83,"qqq_median":15.83,"excess_spy_median":-4.98,"excess_qqq_median":-12.17,"beat_spy_pct":0.0,"beat_qqq_pct":0.0,"best":7.3,"worst":-13.1},"MS":{"n":6,"median":-15.13,"mean":-5.54,"win_rate":33.3,"spy_median":-2.73,"qqq_median":-2.89,"excess_spy_median":-12.4,"excess_qqq_median":-12.18,"beat_spy_pct":33.3,"beat_qqq_pct":16.7,"best":18.4,"worst":-18.6},"BLK":{"n":6,"median":5.34,"mean":1.15,"win_rate":50.0,"spy_median":8.91,"qqq_median":17.18,"excess_spy_median":-3.32,"excess_qqq_median":-6.71,"beat_spy_pct":50.0,"beat_qqq_pct":0.0,"best":13.7,"worst":-18.4},"FDX":{"n":8,"median":3.53,"mean":5.03,"win_rate":75.0,"spy_median":-2.44,"qqq_median":-2.93,"excess_spy_median":2.13,"excess_qqq_median":2.32,"beat_spy_pct":75.0,"beat_qqq_pct":75.0,"best":15.1,"worst":-3.3},"NET":{"n":3,"median":13.52,"mean":17.2,"win_rate":100.0,"spy_median":3.67,"qqq_median":9.23,"excess_spy_median":15.96,"excess_qqq_median":13.45,"beat_spy_pct":100.0,"beat_qqq_pct":100.0,"best":25.3,"worst":12.8},"ULTA":{"n":5,"median":-17.61,"mean":-12.96,"win_rate":0.0,"spy_median":7.58,"qqq_median":13.65,"excess_spy_median":-25.19,"excess_qqq_median":-31.26,"beat_spy_pct":0.0,"beat_qqq_pct":20.0,"best":-0.2,"worst":-22.6},"KMB":{"n":6,"median":0.48,"mean":-0.55,"win_rate":50.0,"spy_median":-3.02,"qqq_median":-2.89,"excess_spy_median":2.96,"excess_qqq_median":3.52,"beat_spy_pct":66.7,"beat_qqq_pct":66.7,"best":3.9,"worst":-6.0},"CVS":{"n":9,"median":1.89,"mean":9.25,"win_rate":55.6,"spy_median":2.37,"qqq_median":3.89,"excess_spy_median":4.43,"excess_qqq_median":2.45,"beat_spy_pct":55.6,"beat_qqq_pct":55.6,"best":28.5,"worst":-5.0},"ARM":{"n":9,"median":67.9,"mean":76.94,"win_rate":100.0,"spy_median":4.92,"qqq_median":12.65,"excess_spy_median":61.42,"excess_qqq_median":53.79,"beat_spy_pct":100.0,"beat_qqq_pct":100.0,"best":158.0,"worst":7.8},"MDT":{"n":5,"median":-10.12,"mean":-11.18,"win_rate":0.0,"spy_median":-3.02,"qqq_median":-2.89,"excess_spy_median":-5.58,"excess_qqq_median":-5.71,"beat_spy_pct":0.0,"beat_qqq_pct":0.0,"best":-8.6,"worst":-17.1},"PFE":{"n":3,"median":-4.81,"mean":-1.62,"win_rate":33.3,"spy_median":10.44,"qqq_median":18.08,"excess_spy_median":-15.25,"excess_qqq_median":-22.89,"beat_spy_pct":33.3,"beat_qqq_pct":33.3,"best":5.2,"worst":-5.2},"AMD":{"n":12,"median":58.49,"mean":43.34,"win_rate":58.3,"spy_median":2.8,"qqq_median":7.8,"excess_spy_median":55.69,"excess_qqq_median":50.69,"beat_spy_pct":58.3,"beat_qqq_pct":58.3,"best":132.0,"worst":-20.9},"DG":{"n":4,"median":-21.9,"mean":-20.6,"win_rate":0.0,"spy_median":5.79,"qqq_median":11.46,"excess_spy_median":-27.69,"excess_qqq_median":-33.36,"beat_spy_pct":0.0,"beat_qqq_pct":0.0,"best":-10.8,"worst":-27.8},"WMT":{"n":8,"median":0.14,"mean":0.49,"win_rate":50.0,"spy_median":10.66,"qqq_median":18.18,"excess_spy_median":-8.57,"excess_qqq_median":-15.33,"beat_spy_pct":25.0,"beat_qqq_pct":25.0,"best":12.8,"worst":-6.3},"TGT":{"n":6,"median":7.83,"mean":8.11,"win_rate":100.0,"spy_median":0.59,"qqq_median":3.02,"excess_spy_median":6.49,"excess_qqq_median":4.05,"beat_spy_pct":83.3,"beat_qqq_pct":50.0,"best":11.6,"worst":5.8},"CAH":{"n":6,"median":-0.53,"mean":0.18,"win_rate":33.3,"spy_median":-4.09,"qqq_median":-3.79,"excess_spy_median":3.94,"excess_qqq_median":1.58,"beat_spy_pct":66.7,"beat_qqq_pct":50.0,"best":8.8,"worst":-6.0},"REGN":{"n":5,"median":-1.55,"mean":-6.49,"win_rate":20.0,"spy_median":-3.58,"qqq_median":-2.85,"excess_spy_median":2.45,"excess_qqq_median":1.3,"beat_spy_pct":60.0,"beat_qqq_pct":60.0,"best":1.1,"worst":-20.4},"CL":{"n":3,"median":-13.59,"mean":-7.0,"win_rate":33.3,"spy_median":3.68,"qqq_median":8.28,"excess_spy_median":-17.27,"excess_qqq_median":-21.86,"beat_spy_pct":33.3,"beat_qqq_pct":33.3,"best":6.8,"worst":-14.2},"MRK":{"n":5,"median":4.32,"mean":6.45,"win_rate":100.0,"spy_median":-3.11,"qqq_median":-3.09,"excess_spy_median":8.82,"excess_qqq_median":7.08,"beat_spy_pct":80.0,"beat_qqq_pct":80.0,"best":14.6,"worst":0.3},"IBM":{"n":6,"median":-6.25,"mean":-1.58,"win_rate":50.0,"spy_median":-0.21,"qqq_median":0.46,"excess_spy_median":-4.5,"excess_qqq_median":-6.58,"beat_spy_pct":50.0,"beat_qqq_pct":16.7,"best":29.5,"worst":-23.3},"ASML":{"n":5,"median":2.25,"mean":2.64,"win_rate":80.0,"spy_median":-3.37,"qqq_median":-3.44,"excess_spy_median":5.27,"excess_qqq_median":5.14,"beat_spy_pct":80.0,"beat_qqq_pct":80.0,"best":20.7,"worst":-13.8},"SNDK":{"n":17,"median":71.94,"mean":74.57,"win_rate":100.0,"spy_median":-3.02,"qqq_median":-3.3,"excess_spy_median":75.3,"excess_qqq_median":75.38,"beat_spy_pct":100.0,"beat_qqq_pct":100.0,"best":154.3,"worst":6.2},"WDC":{"n":26,"median":32.21,"mean":42.86,"win_rate":96.2,"spy_median":2.15,"qqq_median":4.97,"excess_spy_median":35.21,"excess_qqq_median":35.51,"beat_spy_pct":96.2,"beat_qqq_pct":100.0,"best":95.8,"worst":-10.0},"AVGO":{"n":11,"median":-5.28,"mean":-3.71,"win_rate":18.2,"spy_median":-3.37,"qqq_median":-2.89,"excess_spy_median":0.28,"excess_qqq_median":-1.83,"beat_spy_pct":54.5,"beat_qqq_pct":45.5,"best":18.8,"worst":-12.7},"GE":{"n":5,"median":13.62,"mean":11.44,"win_rate":60.0,"spy_median":4.09,"qqq_median":9.45,"excess_spy_median":1.67,"excess_qqq_median":-1.54,"beat_spy_pct":60.0,"beat_qqq_pct":40.0,"best":31.8,"worst":-7.1},"SAN":{"n":5,"median":-9.16,"mean":-6.77,"win_rate":20.0,"spy_median":-3.37,"qqq_median":-2.85,"excess_spy_median":-6.54,"excess_qqq_median":-6.47,"beat_spy_pct":0.0,"beat_qqq_pct":0.0,"best":4.6,"worst":-12.1},"GEV":{"n":11,"median":15.37,"mean":15.6,"win_rate":81.8,"spy_median":5.66,"qqq_median":12.65,"excess_spy_median":7.11,"excess_qqq_median":-1.64,"beat_spy_pct":72.7,"beat_qqq_pct":45.5,"best":38.2,"worst":-7.2},"DHI":{"n":6,"median":-5.67,"mean":-3.62,"win_rate":33.3,"spy_median":0.95,"qqq_median":4.8,"excess_spy_median":-6.97,"excess_qqq_median":-7.87,"beat_spy_pct":0.0,"beat_qqq_pct":0.0,"best":6.3,"worst":-12.2},"UAL":{"n":3,"median":-15.32,"mean":-5.6,"win_rate":33.3,"spy_median":-3.02,"qqq_median":-2.89,"excess_spy_median":-11.22,"excess_qqq_median":-10.73,"beat_spy_pct":33.3,"beat_qqq_pct":33.3,"best":16.4,"worst":-17.9},"AXP":{"n":4,"median":-9.51,"mean":-8.42,"win_rate":25.0,"spy_median":0.06,"qqq_median":2.41,"excess_spy_median":-8.82,"excess_qqq_median":-12.31,"beat_spy_pct":0.0,"beat_qqq_pct":0.0,"best":3.0,"worst":-17.7},"BKNG":{"n":3,"median":-3.58,"mean":-3.38,"win_rate":33.3,"spy_median":3.13,"qqq_median":7.71,"excess_spy_median":-10.15,"excess_qqq_median":-10.28,"beat_spy_pct":33.3,"beat_qqq_pct":0.0,"best":6.6,"worst":-13.2},"MAR":{"n":3,"median":3.81,"mean":5.76,"win_rate":100.0,"spy_median":3.13,"qqq_median":7.71,"excess_spy_median":0.68,"excess_qqq_median":-3.9,"beat_spy_pct":66.7,"beat_qqq_pct":33.3,"best":13.1,"worst":0.4},"RDDT":{"n":6,"median":14.43,"mean":-1.47,"win_rate":66.7,"spy_median":6.11,"qqq_median":12.9,"excess_spy_median":0.49,"excess_qqq_median":-8.73,"beat_spy_pct":50.0,"beat_qqq_pct":33.3,"best":18.9,"worst":-37.5},"BA":{"n":10,"median":-1.06,"mean":-3.84,"win_rate":40.0,"spy_median":5.58,"qqq_median":12.17,"excess_spy_median":-8.46,"excess_qqq_median":-12.55,"beat_spy_pct":0.0,"beat_qqq_pct":0.0,"best":10.4,"worst":-21.1},"UNH":{"n":4,"median":16.12,"mean":11.17,"win_rate":75.0,"spy_median":5.51,"qqq_median":12.88,"excess_spy_median":10.44,"excess_qqq_median":2.21,"beat_spy_pct":75.0,"beat_qqq_pct":75.0,"best":25.6,"worst":-13.1},"LNG":{"n":4,"median":4.76,"mean":2.88,"win_rate":50.0,"spy_median":4.9,"qqq_median":8.82,"excess_spy_median":-0.14,"excess_qqq_median":-4.05,"beat_spy_pct":50.0,"beat_qqq_pct":50.0,"best":21.7,"worst":-19.7},"CAT":{"n":13,"median":8.52,"mean":11.61,"win_rate":100.0,"spy_median":3.03,"qqq_median":6.05,"excess_spy_median":9.71,"excess_qqq_median":10.4,"beat_spy_pct":100.0,"beat_qqq_pct":92.3,"best":28.0,"worst":0.3},"UBER":{"n":7,"median":-2.0,"mean":-2.8,"win_rate":14.3,"spy_median":8.5,"qqq_median":15.83,"excess_spy_median":-8.64,"excess_qqq_median":-15.98,"beat_spy_pct":0.0,"beat_qqq_pct":0.0,"best":1.4,"worst":-8.3},"ET":{"n":5,"median":8.3,"mean":7.84,"win_rate":100.0,"spy_median":-3.02,"qqq_median":-2.89,"excess_spy_median":11.32,"excess_qqq_median":11.19,"beat_spy_pct":80.0,"beat_qqq_pct":80.0,"best":9.5,"worst":5.7},"HSY":{"n":4,"median":-4.45,"mean":-4.82,"win_rate":50.0,"spy_median":0.33,"qqq_median":2.69,"excess_spy_median":-4.94,"excess_qqq_median":-7.64,"beat_spy_pct":50.0,"beat_qqq_pct":50.0,"best":10.1,"worst":-20.5},"STX":{"n":16,"median":30.91,"mean":45.34,"win_rate":93.8,"spy_median":3.74,"qqq_median":6.89,"excess_spy_median":30.59,"excess_qqq_median":30.49,"beat_spy_pct":93.8,"beat_qqq_pct":93.8,"best":117.7,"worst":-18.2},"RTX":{"n":7,"median":-2.85,"mean":-2.49,"win_rate":14.3,"spy_median":3.67,"qqq_median":9.23,"excess_spy_median":2.17,"excess_qqq_median":-0.19,"beat_spy_pct":57.1,"beat_qqq_pct":42.9,"best":9.0,"worst":-9.9},"LMT":{"n":8,"median":-11.56,"mean":-8.88,"win_rate":37.5,"spy_median":5.31,"qqq_median":11.67,"excess_spy_median":-18.64,"excess_qqq_median":-25.72,"beat_spy_pct":37.5,"beat_qqq_pct":37.5,"best":7.0,"worst":-24.2},"TSLA":{"n":6,"median":-13.21,"mean":-7.59,"win_rate":33.3,"spy_median":-4.53,"qqq_median":-5.4,"excess_spy_median":-6.68,"excess_qqq_median":-6.48,"beat_spy_pct":16.7,"beat_qqq_pct":0.0,"best":8.4,"worst":-17.7},"NUE":{"n":7,"median":1.46,"mean":3.93,"win_rate":57.1,"spy_median":3.03,"qqq_median":7.5,"excess_spy_median":-1.63,"excess_qqq_median":-4.19,"beat_spy_pct":42.9,"beat_qqq_pct":42.9,"best":39.1,"worst":-10.9},"COHR":{"n":9,"median":32.87,"mean":36.93,"win_rate":100.0,"spy_median":8.7,"qqq_median":17.02,"excess_spy_median":30.41,"excess_qqq_median":19.33,"beat_spy_pct":100.0,"beat_qqq_pct":100.0,"best":57.4,"worst":21.4},"GM":{"n":5,"median":-3.9,"mean":-5.87,"win_rate":40.0,"spy_median":-4.96,"qqq_median":-6.01,"excess_spy_median":-4.2,"excess_qqq_median":-6.85,"beat_spy_pct":20.0,"beat_qqq_pct":20.0,"best":1.7,"worst":-15.8},"GLW":{"n":8,"median":13.79,"mean":24.68,"win_rate":100.0,"spy_median":4.31,"qqq_median":10.05,"excess_spy_median":16.16,"excess_qqq_median":8.21,"beat_spy_pct":75.0,"beat_qqq_pct":62.5,"best":61.4,"worst":0.3},"CVX":{"n":4,"median":-0.39,"mean":4.16,"win_rate":50.0,"spy_median":6.54,"qqq_median":13.11,"excess_spy_median":-6.94,"excess_qqq_median":-13.5,"beat_spy_pct":25.0,"beat_qqq_pct":25.0,"best":24.0,"worst":-6.6},"XOM":{"n":3,"median":2.43,"mean":5.97,"win_rate":66.7,"spy_median":7.58,"qqq_median":13.65,"excess_spy_median":-5.15,"excess_qqq_median":-11.22,"beat_spy_pct":33.3,"beat_qqq_pct":33.3,"best":22.5,"worst":-7.0},"CMI":{"n":4,"median":5.15,"mean":2.95,"win_rate":50.0,"spy_median":-0.01,"qqq_median":2.32,"excess_spy_median":5.16,"excess_qqq_median":1.1,"beat_spy_pct":75.0,"beat_qqq_pct":50.0,"best":13.9,"worst":-12.4},"NFLX":{"n":6,"median":-5.26,"mean":-6.17,"win_rate":33.3,"spy_median":6.73,"qqq_median":13.35,"excess_spy_median":-13.53,"excess_qqq_median":-20.02,"beat_spy_pct":33.3,"beat_qqq_pct":33.3,"best":9.8,"worst":-21.0},"CMG":{"n":6,"median":-12.0,"mean":-13.45,"win_rate":0.0,"spy_median":-0.73,"qqq_median":1.48,"excess_spy_median":-12.39,"excess_qqq_median":-13.74,"beat_spy_pct":0.0,"beat_qqq_pct":0.0,"best":-8.7,"worst":-21.4},"TXN":{"n":3,"median":-9.93,"mean":-11.21,"win_rate":0.0,"spy_median":-6.08,"qqq_median":-7.19,"excess_spy_median":-3.85,"excess_qqq_median":-2.75,"beat_spy_pct":0.0,"beat_qqq_pct":0.0,"best":-9.9,"worst":-13.8},"NOW":{"n":7,"median":-13.2,"mean":-11.06,"win_rate":14.3,"spy_median":-4.6,"qqq_median":-3.45,"excess_spy_median":-7.89,"excess_qqq_median":-7.19,"beat_spy_pct":28.6,"beat_qqq_pct":14.3,"best":10.6,"worst":-23.6},"LEVI":{"n":3,"median":1.07,"mean":-3.01,"win_rate":66.7,"spy_median":6.0,"qqq_median":14.53,"excess_spy_median":-4.93,"excess_qqq_median":-13.46,"beat_spy_pct":0.0,"beat_qqq_pct":33.3,"best":1.2,"worst":-11.3},"CEG":{"n":3,"median":1.58,"mean":2.35,"win_rate":100.0,"spy_median":-5.32,"qqq_median":-6.01,"excess_spy_median":6.9,"excess_qqq_median":7.59,"beat_spy_pct":100.0,"beat_qqq_pct":100.0,"best":3.9,"worst":1.6},"ETN":{"n":4,"median":4.87,"mean":6.05,"win_rate":50.0,"spy_median":7.02,"qqq_median":13.93,"excess_spy_median":0.18,"excess_qqq_median":-6.7,"beat_spy_pct":50.0,"beat_qqq_pct":50.0,"best":20.2,"worst":-5.7},"BE":{"n":7,"median":39.28,"mean":28.07,"win_rate":71.4,"spy_median":4.09,"qqq_median":9.45,"excess_spy_median":36.25,"excess_qqq_median":31.79,"beat_spy_pct":71.4,"beat_qqq_pct":71.4,"best":58.5,"worst":-23.6},"CARR":{"n":3,"median":7.72,"mean":2.65,"win_rate":66.7,"spy_median":3.09,"qqq_median":8.44,"excess_spy_median":2.22,"excess_qqq_median":0.88,"beat_spy_pct":66.7,"beat_qqq_pct":66.7,"best":9.3,"worst":-9.1},"LUV":{"n":3,"median":-20.94,"mean":-10.07,"win_rate":33.3,"spy_median":-6.08,"qqq_median":-7.19,"excess_spy_median":-14.86,"excess_qqq_median":-13.75,"beat_spy_pct":33.3,"beat_qqq_pct":0.0,"best":11.7,"worst":-20.9},"INTU":{"n":3,"median":-14.32,"mean":-12.94,"win_rate":0.0,"spy_median":-4.6,"qqq_median":-3.45,"excess_spy_median":-9.0,"excess_qqq_median":-8.31,"beat_spy_pct":0.0,"beat_qqq_pct":0.0,"best":-7.6,"worst":-16.9},"MRVL":{"n":10,"median":92.05,"mean":91.35,"win_rate":100.0,"spy_median":5.12,"qqq_median":11.58,"excess_spy_median":87.33,"excess_qqq_median":81.17,"beat_spy_pct":100.0,"beat_qqq_pct":100.0,"best":140.8,"worst":39.2},"HWM":{"n":3,"median":-2.97,"mean":0.26,"win_rate":33.3,"spy_median":4.95,"qqq_median":10.86,"excess_spy_median":-10.55,"excess_qqq_median":-16.62,"beat_spy_pct":33.3,"beat_qqq_pct":33.3,"best":13.4,"worst":-9.7},"PEP":{"n":4,"median":-9.1,"mean":-9.06,"win_rate":0.0,"spy_median":3.84,"qqq_median":8.77,"excess_spy_median":-12.36,"excess_qqq_median":-17.29,"beat_spy_pct":0.0,"beat_qqq_pct":0.0,"best":-7.9,"worst":-10.1},"WDAY":{"n":4,"median":-12.31,"mean":-14.32,"win_rate":0.0,"spy_median":4.22,"qqq_median":9.11,"excess_spy_median":-16.79,"excess_qqq_median":-21.01,"beat_spy_pct":0.0,"beat_qqq_pct":0.0,"best":-10.9,"worst":-21.7},"VRT":{"n":6,"median":27.59,"mean":22.97,"win_rate":100.0,"spy_median":8.72,"qqq_median":17.01,"excess_spy_median":14.45,"excess_qqq_median":7.12,"beat_spy_pct":83.3,"beat_qqq_pct":83.3,"best":31.8,"worst":4.5},"GNRC":{"n":4,"median":12.39,"mean":13.1,"win_rate":75.0,"spy_median":4.52,"qqq_median":10.16,"excess_spy_median":7.87,"excess_qqq_median":2.24,"beat_spy_pct":75.0,"beat_qqq_pct":75.0,"best":34.0,"worst":-6.3},"TJX":{"n":5,"median":-0.11,"mean":-1.27,"win_rate":40.0,"spy_median":9.24,"qqq_median":17.38,"excess_spy_median":-12.29,"excess_qqq_median":-20.9,"beat_spy_pct":0.0,"beat_qqq_pct":0.0,"best":1.1,"worst":-5.7},"SOFI":{"n":4,"median":-1.11,"mean":2.67,"win_rate":50.0,"spy_median":4.05,"qqq_median":9.36,"excess_spy_median":-4.67,"excess_qqq_median":-9.6,"beat_spy_pct":25.0,"beat_qqq_pct":25.0,"best":17.2,"worst":-4.3},"ANET":{"n":4,"median":1.49,"mean":6.95,"win_rate":50.0,"spy_median":3.4,"qqq_median":8.84,"excess_spy_median":-2.99,"excess_qqq_median":-10.17,"beat_spy_pct":25.0,"beat_qqq_pct":25.0,"best":29.8,"worst":-5.0},"DIS":{"n":3,"median":-4.31,"mean":-4.85,"win_rate":0.0,"spy_median":3.68,"qqq_median":9.23,"excess_spy_median":-8.93,"excess_qqq_median":-15.86,"beat_spy_pct":0.0,"beat_qqq_pct":0.0,"best":-3.6,"worst":-6.6},"CIEN":{"n":4,"median":16.44,"mean":19.12,"win_rate":50.0,"spy_median":6.85,"qqq_median":15.0,"excess_spy_median":4.34,"excess_qqq_median":-5.19,"beat_spy_pct":50.0,"beat_qqq_pct":50.0,"best":51.3,"worst":-7.7},"DELL":{"n":7,"median":55.56,"mean":65.58,"win_rate":100.0,"spy_median":10.05,"qqq_median":17.0,"excess_spy_median":45.51,"excess_qqq_median":38.56,"beat_spy_pct":100.0,"beat_qqq_pct":100.0,"best":105.6,"worst":36.9},"MP":{"n":4,"median":-3.45,"mean":-3.26,"win_rate":25.0,"spy_median":5.15,"qqq_median":12.07,"excess_spy_median":-10.04,"excess_qqq_median":-18.45,"beat_spy_pct":0.0,"beat_qqq_pct":0.0,"best":4.6,"worst":-10.7},"LYB":{"n":3,"median":-11.21,"mean":-3.87,"win_rate":33.3,"spy_median":15.77,"qqq_median":27.11,"excess_spy_median":-27.19,"excess_qqq_median":-38.48,"beat_spy_pct":33.3,"beat_qqq_pct":0.0,"best":12.1,"worst":-12.5},"DOW":{"n":3,"median":-14.75,"mean":-6.82,"win_rate":33.3,"spy_median":9.12,"qqq_median":17.36,"excess_spy_median":-25.44,"excess_qqq_median":-33.37,"beat_spy_pct":33.3,"beat_qqq_pct":0.0,"best":14.4,"worst":-20.1},"BX":{"n":4,"median":0.38,"mean":-0.06,"win_rate":50.0,"spy_median":8.8,"qqq_median":16.59,"excess_spy_median":-9.29,"excess_qqq_median":-17.09,"beat_spy_pct":0.0,"beat_qqq_pct":0.0,"best":3.1,"worst":-4.1},"ABNB":{"n":3,"median":-0.18,"mean":1.45,"win_rate":33.3,"spy_median":13.42,"qqq_median":22.03,"excess_spy_median":-10.38,"excess_qqq_median":-21.83,"beat_spy_pct":0.0,"beat_qqq_pct":0.0,"best":8.0,"worst":-3.5},"MKC":{"n":3,"median":-7.65,"mean":-8.7,"win_rate":0.0,"spy_median":16.69,"qqq_median":28.68,"excess_spy_median":-24.35,"excess_qqq_median":-36.34,"beat_spy_pct":0.0,"beat_qqq_pct":0.0,"best":-6.7,"worst":-11.8},"VIK":{"n":3,"median":27.92,"mean":26.0,"win_rate":100.0,"spy_median":8.69,"qqq_median":18.36,"excess_spy_median":9.56,"excess_qqq_median":-1.89,"beat_spy_pct":100.0,"beat_qqq_pct":33.3,"best":33.6,"worst":16.5},"LUMN":{"n":8,"median":1.15,"mean":10.95,"win_rate":50.0,"spy_median":7.06,"qqq_median":15.68,"excess_spy_median":-5.57,"excess_qqq_median":-14.32,"beat_spy_pct":50.0,"beat_qqq_pct":37.5,"best":52.5,"worst":-17.6},"VZ":{"n":3,"median":-0.56,"mean":-2.5,"win_rate":33.3,"spy_median":8.5,"qqq_median":15.83,"excess_spy_median":-9.07,"excess_qqq_median":-16.4,"beat_spy_pct":0.0,"beat_qqq_pct":0.0,"best":0.8,"worst":-7.7}}}