{"company": "CoreWeave", "mentions": [{"date": "2026-05-01", "sentiment": "buy_on_pullback", "segment": "opening_commentary", "note": "Heavily shorted; CEO Brodman Tren building new data centers aggressively; could pop if no financing dilution; convertible deal possible\u2014stock could pop if avoids equity raise.", "closing_price": 340.94}, {"date": "2026-02-23", "sentiment": "buy", "segment": "in_depth_analysis", "note": "EDA design software rallied after strong quarter despite AI disruption narrative; insulated from low-code threats; showing floor for quality software stocks.", "closing_price": 279.8}]}