{"company": "Vita Coco", "mentions": [{"date": "2026-03-02", "sentiment": "wait_hold_neutral", "segment": "lightning_round", "note": "Started mid-20s, now mid-to-high 50s; strong double-digit EBITDA growth despite tariff costs; hold position near 52-week high, don't add.", "closing_price": 54.45}, {"date": "2026-04-09", "sentiment": "buy", "segment": "in_depth_analysis", "note": "30% earnings growth, dominant 42-80% market share in coconut water, $200M cash zero debt; 20% recent pullback offers rare entry for long-term wealth builder despite 32x current earnings valuation.", "closing_price": 48.83}], "sector": "Consumer Defensive", "style": "growth", "industry": "Beverages - Non-Alcoholic", "pe_ratio": 53.41, "market_cap": 4209773056, "market_cap_category": "mid", "price_latest": 68.98, "price_latest_date": "2026-07-01", "pct_right_daily": 87.7, "n_right_days": 57, "days_right": {"buy": {"pct": 87.7, "n": 57, "small_sample": false}, "combined": {"pct": 87.7, "n": 57, "small_sample": false}, "hold_wait": {"fell_pct": 63.0, "rose_pct": 37.0, "n": 27, "small_sample": true}}}