{"company": "Darden Restaurants", "mentions": [{"date": "2026-04-07", "sentiment": "caution_concern", "segment": "opening_commentary", "note": "Parent of Olive Garden down 3%; screaming for help; consumer eating out less.", "closing_price": 190.63}, {"date": "2026-06-18", "sentiment": "buy", "segment": "opening_commentary", "note": "Fabulous restaurant chain (Olive Garden); almost always surprises upside like clockwork. Gas prices coming down and that historically drives Darden performance for 25 years I followed it.", "closing_price": 213.45}], "sector": "Consumer Cyclical", "style": "blend", "industry": "Restaurants", "pe_ratio": 20.49, "market_cap": 24478420992, "market_cap_category": "large", "price_latest": 201.95, "price_latest_date": "2026-07-01", "pct_right_daily": 1.7, "n_right_days": 59, "days_right": {"buy": {"pct": 12.5, "n": 8, "small_sample": true, "calls": 1}, "sell": {"pct": 0.0, "n": 51, "small_sample": false, "calls": 1}, "combined": {"pct": 1.7, "n": 59, "small_sample": false, "calls": 2}}}