{"company": "Enphase Energy", "mentions": [{"date": "2026-03-05", "sentiment": "sell_avoid", "segment": "lightning_round", "note": "No conviction on battery/solar thesis near-term; caller wanted quick in-and-out; too risky to trade.", "closing_price": 41.15}, {"date": "2026-04-15", "sentiment": "caution_concern", "segment": "lightning_round", "note": "Solar inverter company; 2% margin headwind from tariffs becoming tailwind under IFTA ruling. Disappointing stock; Cramer prefers First Solar despite upside potential.", "closing_price": 32.18}], "sector": "Technology", "style": "growth", "industry": "Solar", "pe_ratio": 47.11, "market_cap": 6270959616, "market_cap_category": "mid", "price_latest": 52.28, "price_latest_date": "2026-06-18", "pct_right_daily": 27.4, "n_right_days": 73}