{"company": "Fubo", "mentions": [{"date": "2026-06-12", "sentiment": "sell_avoid", "segment": "closing_commentary", "note": "Media sector in secular decline; Disney's 70% stake and NBC Universal partnership don't change fundamentals; industry is broken; can't recommend media no matter how cheap it looks.", "closing_price": 9.83}, {"date": "2026-06-12", "sentiment": "sell_avoid", "segment": "caller_qa", "note": "Media sector in secular decline; Disney 70% investment and NBC Universal deal irrelevant; avoid pure media plays regardless of valuation.", "closing_price": 9.83}], "sector": "Communication Services", "industry": "Broadcasting", "style": "value", "pe_ratio": 2.58, "market_cap": 291706752, "market_cap_category": "micro", "price_latest": 8.07, "price_latest_date": "2026-06-25", "pct_right_daily": 87.5, "n_right_days": 8}