{"company": "Home Depot", "mentions": [{"date": "2026-04-02", "sentiment": "caution_concern", "segment": "caller_qa", "note": "Down 8% today, hit 52-week low; 3% yield attractive but mortgage rates must decline first for demand recovery; ICE-related issues hurt; hold existing but don't add until rate clarity emerges.", "price_level": 19, "closing_price": 14.25}], "sector": "Consumer Cyclical", "style": "blend", "industry": "Restaurants", "pe_ratio": 25.16, "market_cap": 740164416, "market_cap_category": "small"}