{"company": "MLI", "sector": "Industrials", "style": "blend", "mentions": [{"date": "2026-01-27", "sentiment": "buy", "segment": "lightning_round", "note": "Straight up since bankruptcy; slow-and-steady pipes and infrastructure play; insider selling notwithstanding, Cramer remains buyer of this quality company.", "closing_price": 134.43}], "industry": "Metal Fabrication", "pe_ratio": 16.8, "market_cap": 14175152128, "market_cap_category": "large", "price_latest": 58.39, "price_latest_date": "2026-07-14", "pct_right_daily": 0.0, "n_right_days": 115, "days_right": {"buy": {"pct": 0.0, "n": 115, "small_sample": false, "calls": 1}, "combined": {"pct": 0.0, "n": 115, "small_sample": false, "calls": 1}}}