{"company": "Navitas Semiconductor", "mentions": [{"date": "2026-03-11", "sentiment": "wait_hold_neutral", "segment": "lightning_round", "note": "Caller Mark (WI): semiconductor, burning cash but partnered with Nvidia; Cramer: good technology that should translate to earnings, not done so yet, ride it.", "closing_price": 10.84}], "sector": "Technology", "style": "", "industry": "Semiconductors", "pe_ratio": null, "market_cap": 4213503488, "market_cap_category": "mid", "price_latest": 16.53, "price_latest_date": "2026-07-01", "days_right": {"hold_wait": {"fell_pct": 31.2, "rose_pct": 68.8, "n_fell": 24, "n_rose": 53, "calls": 1, "small_sample": false}}}