{"company": "Oscar Health", "mentions": [{"date": "2026-03-27", "sentiment": "buy", "segment": "lightning_round", "note": "Health insurance stock led by Mark Bertolini and Joshua Kushner; recently broken down to $11; buy half here and half at $9 if it gets there; otherwise just own it\u2014good opportunity.", "price_level": 11, "closing_price": 11.14}, {"date": "2026-01-16", "sentiment": "strong_buy", "segment": "lightning_round", "note": "CEO Mark Bertellini strong; ACA membership +30% YoY, revenue +20%; tax credits likely extended; setup for breakout year.", "closing_price": 16.55}], "sector": "Healthcare", "style": ""}