{"company": "Quantee Electronics", "mentions": [{"date": "2026-03-25", "sentiment": "buy", "segment": "lightning_round", "note": "DuPont spin-off, up 70% since IPO 5mo ago; beats earnings estimates; materials for semiconductor manufacturing; club holding; still inexpensive at 30-31x earnings.", "closing_price": 220.85}], "price_latest": 326.1, "price_latest_date": "2026-07-01", "pct_right_daily": 91.0, "n_right_days": 67, "days_right": {"buy": {"pct": 91.0, "n": 67, "small_sample": false, "calls": 1}, "combined": {"pct": 91.0, "n": 67, "small_sample": false, "calls": 1}}}