{"company": "Sterling Infrastructure", "mentions": [{"date": "2026-05-05", "sentiment": "strong_buy", "segment": "opening_commentary", "note": "Data center construction; reported tremendous quarter, stock up 52% (+276 points); beneficiary of buildout wave.", "closing_price": 131.62}, {"date": "2026-07-15", "sentiment": "buy", "segment": "lightning_round", "note": "Jeff (South Africa living caller) bought on dip, stock keeps dipping 10% past 3 months but numbers solid. Cramer recommends buy\u2014road builder should be bought, likely consolidation candidate.", "closing_price": 103.86}], "price_latest": 103.86, "price_latest_date": "2026-07-15", "pct_right_daily": 6.2, "n_right_days": 48, "days_right": {"buy": {"pct": 6.2, "n": 48, "small_sample": false, "calls": 2}, "combined": {"pct": 6.2, "n": 48, "small_sample": false, "calls": 2}}}