{"company": "Teladoc Health", "mentions": [{"date": "2026-02-02", "sentiment": "sell_avoid", "segment": "lightning_round", "note": "Down 96% in IRA (no tax-loss benefit); Cramer: 'I don't see any reason to own it.' Many competitors in telehealth space; wishing won't recover it.", "closing_price": 5.37}], "sector": "Healthcare", "style": "", "industry": "Health Information Services", "pe_ratio": null, "market_cap": 1514504832, "market_cap_category": "small", "price_latest": 8.07, "price_latest_date": "2026-06-18"}