{"company": "Ventas", "mentions": [{"date": "2026-04-02", "sentiment": "strong_buy", "segment": "in_depth_analysis", "note": "Senior housing REIT led by Deb Cafaro; ~20% average annual gain 2+ decades; 2,100% gain since 2000 (9,200% with dividends); 112% 3-year return; 60% of earnings senior housing, 80K units; 2.5% yield; cheapest valuation (26x 2026 FFO) with best yield; 'the one who brought us'\u2014best long-term hold in senior housing space.", "closing_price": 83.27}, {"date": "2026-04-28", "sentiment": "strong_buy", "segment": "interview", "note": "Q1 beat-and-raise; 70M baby boomers turning 80 starting 2026 creates decade+ growth runway. 87% occupied, historic supply lows, 19% CAGR track record.", "closing_price": 87.57}], "sector": "Real Estate", "style": "growth", "industry": "REIT - Healthcare Facilities", "pe_ratio": 161.91, "market_cap": 43293417472, "market_cap_category": "large", "price_latest": 89.65, "price_latest_date": "2026-07-01", "pct_right_daily": 50.8, "n_right_days": 61}